ECOv002_granules/ECOv002_granules.py
ECOv002_granules/L1CTRAD.py
ECOv002_granules/L2TLSTE.py
ECOv002_granules/L2TSTARS.py
ECOv002_granules/L3TJET.py
ECOv002_granules/L3TMET.py
ECOv002_granules/L3TSEB.py
ECOv002_granules/L3TSM.py
ECOv002_granules/L4TESI.py
ECOv002_granules/L4TWUE.py
ECOv002_granules/__init__.py
ECOv002_granules/colors.py
ECOv002_granules/constants.py
ECOv002_granules/granule.py
ECOv002_granules/open_granule.py
ECOv002_granules/tiled_granule.py
ECOv002_granules/version.py
ECOv002_granules/write_L3T_JET.py
ECOv002_granules/write_L3T_MET.py
ECOv002_granules/write_L3T_SEB.py
ECOv002_granules/write_L3T_SM.py
ECOv002_granules/write_L4T_ESI.py
ECOv002_granules/write_L4T_WUE.py
ECOv002_granules/write_XML_metadata.py
ECOv002_granules/timer/__init__.py
ECOv002_granules/timer/timer.py
ecov002_granules-1.2.1.dist-info/licenses/LICENSE
ecov002_granules-1.2.1.dist-info/METADATA
ecov002_granules-1.2.1.dist-info/WHEEL
ecov002_granules-1.2.1.dist-info/top_level.txt
ecov002_granules-1.2.1.dist-info/RECORD
